uff_widget.py
uff_widget-0.2.dist-info/LICENSE
uff_widget-0.2.dist-info/METADATA
uff_widget-0.2.dist-info/WHEEL
uff_widget-0.2.dist-info/top_level.txt
uff_widget-0.2.dist-info/RECORD
