Metadata-Version: 2.1
Name: uff-widget
Version: 0.2
Summary: Visualization of uff file
Home-page: https://github.com/ladisk/uff_widget
Author: Lovro Trilar,Janko Slavič
Author-email: Lovro.3lar@gmail.com, janko.slavic@fs.uni-lj.si
License: UNKNOWN
Platform: UNKNOWN
Classifier: Programming Language :: Python :: 3
Classifier: License :: OSI Approved :: MIT License
Classifier: Operating System :: OS Independent
Requires-Dist: numpy (>=1.16.1)
Requires-Dist: pyuff (>=1.20)
Requires-Dist: ipywidgets (>=7.4.2)
Requires-Dist: ipyvolume (>=0.5.1)
Requires-Dist: ipython (>=6.2.1)
